exonwebui/__init__.py
exonwebui/flask/menuboard.py
exonwebui/flask/macros/__init__.py
exonwebui/flask/macros/basic.py
exonwebui/flask/macros/datagrids.py
exonwebui/flask/macros/forms.py
exonwebui/flask/utils/__init__.py
exonwebui/flask/utils/gzip.py
exonwebui/flask/utils/locale.py
exonwebui/static/css/webui.css
exonwebui/static/css/webui.min.css
exonwebui/static/css/webui_datagrid.css
exonwebui/static/css/webui_datagrid.min.css
exonwebui/static/css/webui_inputform.css
exonwebui/static/css/webui_inputform.min.css
exonwebui/static/css/webui_menuboard.css
exonwebui/static/css/webui_menuboard.min.css
exonwebui/static/css/webui_simpleboard.css
exonwebui/static/css/webui_simpleboard.min.css
exonwebui/static/images/loader.gif
exonwebui/static/js/i18n/webui.js
exonwebui/static/js/i18n/webui.min.js
exonwebui/static/js/i18n/webui_menuboard.js
exonwebui/static/js/i18n/webui_menuboard.min.js
exonwebui/static/js/i18n/webui_simpleboard.js
exonwebui/static/js/i18n/webui_simpleboard.min.js
exonwebui/templates/jinja2/i18n/html.j2
exonwebui/templates/jinja2/i18n/menuboard.j2
exonwebui/templates/jinja2/i18n/simpleboard.j2
exonwebui/templates/jinja2/i18n/simplepage.j2
exonwebui/templates/jinja2/i18n/macros/cdn.j2
exonwebui/templates/jinja2/i18n/macros/basic/alert.j2
exonwebui/templates/jinja2/i18n/macros/basic/asyncmodal.j2
exonwebui/templates/jinja2/i18n/macros/basic/linkmodal.j2
exonwebui/templates/jinja2/i18n/macros/datagrids/stddatagrid.j2
exonwebui/templates/jinja2/i18n/macros/forms/inputform.j2
exonwebui/templates/jinja2/i18n/macros/forms/loginform.j2
exonwebui/templates/jinja2/i18n/macros/forms/qbuilder.j2
exonwebui-7.3.dist-info/LICENSE.txt
exonwebui-7.3.dist-info/METADATA
exonwebui-7.3.dist-info/WHEEL
exonwebui-7.3.dist-info/top_level.txt
exonwebui-7.3.dist-info/RECORD
