Metadata-Version: 2.1
Name: exonwebui
Version: 7.3
Summary: Simple lightweight libs for UI web applications.
Author-email: ExonLabs <info@exonlabs.net>
License: BSD 3-Clause License
Project-URL: Documentation, https://exonlabs.github.io/py-exonwebui
Project-URL: Repository, https://github.com/exonlabs/py-exonwebui
Classifier: Development Status :: 5 - Production/Stable
Classifier: Intended Audience :: Developers
Classifier: License :: OSI Approved :: BSD License
Classifier: Operating System :: OS Independent
Classifier: Programming Language :: Python
Classifier: Programming Language :: Python :: 3.9
Classifier: Programming Language :: Python :: 3.10
Classifier: Programming Language :: Python :: 3.11
Classifier: Programming Language :: Python :: 3.12
Classifier: Topic :: Software Development :: Libraries
Classifier: Topic :: Software Development :: Libraries :: Python Modules
Requires-Python: >=3.9
License-File: LICENSE.txt
Requires-Dist: exonweb <8.0,>=7.0
Requires-Dist: exonwebui-static <2.0,>=1.0
Requires-Dist: Babel <3.0,>=2.16
Requires-Dist: flask-babelex <1.0,>=0.9
Requires-Dist: pytz <2025.0,>=2024.1
Provides-Extra: dev
